pyproforma/__init__.py
pyproforma/constants.py
pyproforma/data_import.py
pyproforma/charts/__init__.py
pyproforma/charts/chart_class.py
pyproforma/charts/charts.py
pyproforma/models/__init__.py
pyproforma/models/_utils.py
pyproforma/models/category.py
pyproforma/models/compare.py
pyproforma/models/constraint.py
pyproforma/models/formula.py
pyproforma/models/line_item.py
pyproforma/models/generator/__init__.py
pyproforma/models/generator/abc_class.py
pyproforma/models/generator/debt.py
pyproforma/models/generator/short_term_debt.py
pyproforma/models/metadata/__init__.py
pyproforma/models/metadata/metadata.py
pyproforma/models/model/__init__.py
pyproforma/models/model/model.py
pyproforma/models/model/model_update.py
pyproforma/models/model/serialization.py
pyproforma/models/model/validations.py
pyproforma/models/model/value_matrix.py
pyproforma/models/results/__init__.py
pyproforma/models/results/category_results.py
pyproforma/models/results/constraint_results.py
pyproforma/models/results/line_item_results.py
pyproforma/models/results/line_items_results.py
pyproforma/tables/__init__.py
pyproforma/tables/compare.py
pyproforma/tables/excel.py
pyproforma/tables/row_types.py
pyproforma/tables/table_class.py
pyproforma/tables/table_generator.py
pyproforma/tables/tables.py
pyproforma-0.1.15.dist-info/licenses/LICENSE
pyproforma-0.1.15.dist-info/METADATA
pyproforma-0.1.15.dist-info/WHEEL
pyproforma-0.1.15.dist-info/top_level.txt
pyproforma-0.1.15.dist-info/RECORD
