Metadata-Version: 2.4
Name: pyproforma
Version: 0.1.15
Summary: A Python package for financial modeling and reporting
Author-email: Robert Hannay <rhannay@gmail.com>
Maintainer-email: Robert Hannay <rhannay@gmail.com>
License-Expression: MIT
Project-URL: Homepage, https://github.com/rhannay/pyproforma
Project-URL: Repository, https://github.com/rhannay/pyproforma
Project-URL: Documentation, https://pyproforma.readthedocs.io/en/latest/
Project-URL: Issues, https://github.com/rhannay/pyproforma/issues
Keywords: finance,modeling,reporting,excel,proforma
Classifier: Development Status :: 4 - Beta
Classifier: Intended Audience :: Financial and Insurance Industry
Classifier: Topic :: Office/Business :: Financial
Classifier: Programming Language :: Python :: 3
Classifier: Programming Language :: Python :: 3.9
Classifier: Programming Language :: Python :: 3.10
Classifier: Programming Language :: Python :: 3.11
Classifier: Programming Language :: Python :: 3.12
Classifier: Operating System :: OS Independent
Requires-Python: >=3.9
License-File: LICENSE
Requires-Dist: pandas>=1.3.0
Requires-Dist: openpyxl>=3.0.0
Requires-Dist: jinja2>=3.0.0
Requires-Dist: plotly>=5.0.0
Requires-Dist: PyYAML>=6.0.0
Requires-Dist: nbformat>=5.0.0
Provides-Extra: dev
Requires-Dist: pytest>=6.0; extra == "dev"
Requires-Dist: pytest-cov; extra == "dev"
Dynamic: license-file
